multiurl/MANIFEST.in
multiurl/README.md
multiurl/__init__.py
multiurl/apps.py
multiurl/multiurl.py
multiurl/setup.py
multiurl/tests.py
django_multiurl_for_garpix_page-1.6.0.dist-info/METADATA
django_multiurl_for_garpix_page-1.6.0.dist-info/WHEEL
django_multiurl_for_garpix_page-1.6.0.dist-info/top_level.txt
django_multiurl_for_garpix_page-1.6.0.dist-info/RECORD
